README.rst
oddfisher/__init__.py
oddfisher/fisher.py
setup.cfg
oddfisher-0.1.1.dist-info/LICENSE
oddfisher-0.1.1.dist-info/METADATA
oddfisher-0.1.1.dist-info/WHEEL
oddfisher-0.1.1.dist-info/entry_points.txt
oddfisher-0.1.1.dist-info/RECORD
