Metadata-Version: 2.1
Name: oddfisher
Version: 0.1.1
Summary: 
Author: allen choi
Author-email: choiae0417@gmail.com
Requires-Python: >=3.10
Classifier: Programming Language :: Python :: 3
Classifier: Programming Language :: Python :: 3.10
Classifier: Programming Language :: Python :: 3.11
Classifier: Programming Language :: Python :: 3.12
Requires-Dist: numpy (>=2.0.1)
Requires-Dist: pandas (>=2.2.2)
Requires-Dist: pytest-cov (>=5.0.0,<6.0.0)
Requires-Dist: scipy (>=1.14.0)
